dynamicadaptor/AddonCard.py
dynamicadaptor/Content.py
dynamicadaptor/DynamicConversion.py
dynamicadaptor/Header.py
dynamicadaptor/Majors.py
dynamicadaptor/Message.py
dynamicadaptor/Repost.py
dynamicadaptor/__init__.py
dynamicadaptor-0.5.5.dist-info/LICENSE
dynamicadaptor-0.5.5.dist-info/METADATA
dynamicadaptor-0.5.5.dist-info/WHEEL
dynamicadaptor-0.5.5.dist-info/RECORD
