Metadata-Version: 2.1
Name: DynamicAdaptor
Version: 0.5.5
Summary: 
Author: DMC
Author-email: lzxder@outlook.com
Requires-Python: >=3.8.0,<4.0.0
Classifier: Programming Language :: Python :: 3
Classifier: Programming Language :: Python :: 3.8
Classifier: Programming Language :: Python :: 3.9
Classifier: Programming Language :: Python :: 3.10
Classifier: Programming Language :: Python :: 3.11
Classifier: Programming Language :: Python :: 3.12
Requires-Dist: loguru (>=0.6.0,<0.7.0)
Requires-Dist: pydantic (>=2.0.0,<3.0.0)
